pizurscan/InputProcessor.py
pizurscan/InputValidator.py
pizurscan/OutputProcessor.py
pizurscan/PI_commands.py
pizurscan/Scanner.py
pizurscan/__init__.py
pizurscan/test.py
pizurscan-0.1.9.dist-info/METADATA
pizurscan-0.1.9.dist-info/WHEEL
pizurscan-0.1.9.dist-info/top_level.txt
pizurscan-0.1.9.dist-info/RECORD
