Metadata-Version: 2.1
Name: pizurscan
Version: 0.1.9
Summary: Library to interface PI controllers and Zurich lock-in
Home-page: https://pizur-scanner.readthedocs.io/
Author: Giacomo Rizzi
Author-email: rizzigiacomo@pm.me
License: MIT
Classifier: Intended Audience :: Developers
Classifier: License :: OSI Approved :: MIT License
Classifier: Programming Language :: Python
Classifier: Programming Language :: Python :: 3
Classifier: Programming Language :: Python :: 3.6
Classifier: Programming Language :: Python :: 3.7
Classifier: Programming Language :: Python :: 3.8
Classifier: Programming Language :: Python :: 3.9
Classifier: Operating System :: Microsoft :: Windows
Requires-Dist: numpy
